Workbook

Sheet Clashbook
A1: Cashbook - Daily Income & Expanses
E3: 0 | I3: Daily revenue report
C4: Total Income | E4: =SUM(E9:E508) -> 7000000 | F4: check | G4: =IF(COUNT(A9:A508)=0,0,ROUND(E6-INDEX(G9:G508,MATCH(9.99E+307,G9:G508)),2)) -> 0 | I4: Select Date | J4: 46113
C5: Total Expenses | E5: =SUM(F9:F508) -> 5577000 | G5: =IF(G4=0,"✔ Check pass","✘ Check again") -> ✔ Check pass | I5: day's income | J5: =SUMIFS(E9:E508,A9:A508,J4) -> 700000
C6: Closing Balance | E6: =E3+E4-E5 -> 1423000 | F6: No. of item | G6: =COUNT(A9:A508) -> 105 | I6: day's expenses | J6: =SUMIFS(F9:F508,A9:A508,J4) -> 130000
I7: Net amount | J7: =J5-J6 -> 570000
A8: Date | B8: Day | C8: List | D8: Category | E8: Income | F8: Expenses | G8: Balance
A9: 46113 | B9: =IF(A9="","",TEXT(A9,"dddd")) -> Wednesday | C9: Weekly allowance | D9: Money | E9: 700000 | G9: =IF(A9="","",$E$3+SUM($E$9:E9)-SUM($F$9:F9)) -> 700000
A10: 46113 | B10: =IF(A10="","",TEXT(A10,"dddd")) -> Wednesday | C10: Meals | F10: 50000 | G10: =IF(A10="","",$E$3+SUM($E$9:E10)-SUM($F$9:F10)) -> 650000
A11: 46113 | B11: =IF(A11="","",TEXT(A11,"dddd")) -> Wednesday | C11: Coffee | F11: 30000 | G11: =IF(A11="","",$E$3+SUM($E$9:E11)-SUM($F$9:F11)) -> 620000
A12: 46113 | B12: =IF(A12="","",TEXT(A12,"dddd")) -> Wednesday | C12: Meals | F12: 50000 | G12: =IF(A12="","",$E$3+SUM($E$9:E12)-SUM($F$9:F12)) -> 570000
A13: 46114 | B13: =IF(A13="","",TEXT(A13,"dddd")) -> Thursday | C13: Meals | F13: 50000 | G13: =IF(A13="","",$E$3+SUM($E$9:E13)-SUM($F$9:F13)) -> 520000
A14: 46114 | B14: =IF(A14="","",TEXT(A14,"dddd")) -> Thursday | C14: Snack | F14: 20000 | G14: =IF(A14="","",$E$3+SUM($E$9:E14)-SUM($F$9:F14)) -> 500000
A15: 46114 | B15: =IF(A15="","",TEXT(A15,"dddd")) -> Thursday | C15: Snack | F15: 15000 | G15: =IF(A15="","",$E$3+SUM($E$9:E15)-SUM($F$9:F15)) -> 485000
A16: 46114 | B16: =IF(A16="","",TEXT(A16,"dddd")) -> Thursday | C16: Meals | F16: 50000 | G16: =IF(A16="","",$E$3+SUM($E$9:E16)-SUM($F$9:F16)) -> 435000
A17: 46115 | B17: =IF(A17="","",TEXT(A17,"dddd")) -> Friday | C17: Water | F17: 10000 | G17: =IF(A17="","",$E$3+SUM($E$9:E17)-SUM($F$9:F17)) -> 425000
A18: 46115 | B18: =IF(A18="","",TEXT(A18,"dddd")) -> Friday | C18: Coffee | F18: 30000 | G18: =IF(A18="","",$E$3+SUM($E$9:E18)-SUM($F$9:F18)) -> 395000
A19: 46115 | B19: =IF(A19="","",TEXT(A19,"dddd")) -> Friday | C19: Meals | F19: 50000 | G19: =IF(A19="","",$E$3+SUM($E$9:E19)-SUM($F$9:F19)) -> 345000
A20: 46116 | B20: =IF(A20="","",TEXT(A20,"dddd")) -> Saturday | C20: Meals | F20: 50000 | G20: =IF(A20="","",$E$3+SUM($E$9:E20)-SUM($F$9:F20)) -> 295000
A21: 46116 | B21: =IF(A21="","",TEXT(A21,"dddd")) -> Saturday | C21: Meals | F21: 50000 | G21: =IF(A21="","",$E$3+SUM($E$9:E21)-SUM($F$9:F21)) -> 245000
... A24: 46118 | B24: =IF(A24="","",TEXT(A24,"dddd")) -> Monday | C24: Meals | F24: 50000 | G24: =IF(A24="","",$E$3+SUM($E$9:E24)-SUM($F$9:F24)) -> 115000
A25: 46120 | B25: =IF(A25="","",TEXT(A25,"dddd")) -> Wednesday | C25: Weekly allowance | D25: Money | E25: 700000 | G25: =IF(A25="","",$E$3+SUM($E$9:E25)-SUM($F$9:F25)) -> 815000
A26: 46120 | B26: =IF(A26="","",TEXT(A26,"dddd")) -> Wednesday | C26: Meals | F26: 50000 | G26: =IF(A26="","",$E$3+SUM($E$9:E26)-SUM($F$9:F26)) -> 765000
A27: 46121 | B27: =IF(A27="","",TEXT(A27,"dddd")) -> Thursday | C27: Coffee | F27: 30000 | G27: =IF(A27="","",$E$3+SUM($E$9:E27)-SUM($F$9:F27)) -> 735000
A28: 46121 | B28: =IF(A28="","",TEXT(A28,"dddd")) -> Thursday | C28: Meals | F28: 50000 | G28: =IF(A28="","",$E$3+SUM($E$9:E28)-SUM($F$9:F28)) -> 685000
A29: 46122 | B29: =IF(A29="","",TEXT(A29,"dddd")) -> Friday | C29: Meals | F29: 50000 | G29: =IF(A29="","",$E$3+SUM($E$9:E29)-SUM($F$9:F29)) -> 635000
A30: 46123 | B30: =IF(A30="","",TEXT(A30,"dddd")) -> Saturday | C30: Meals | F30: 50000 | G30: =IF(A30="","",$E$3+SUM($E$9:E30)-SUM($F$9:F30)) -> 585000
A31: 46124 | B31: =IF(A31="","",TEXT(A31,"dddd")) -> Sunday | C31: Meals | F31: 50000 | G31: =IF(A31="","",$E$3+SUM($E$9:E31)-SUM($F$9:F31)) -> 535000
A32: 46125 | B32: =IF(A32="","",TEXT(A32,"dddd")) -> Monday | C32: BBQ | F32: 150000 | G32: =IF(A32="","",$E$3+SUM($E$9:E32)-SUM($F$9:F32)) -> 385000
A33: 46126 | B33: =IF(A33="","",TEXT(A33,"dddd")) -> Tuesday | C33: Coffee | F33: 50000 | G33: =IF(A33="","",$E$3+SUM($E$9:E33)-SUM($F$9:F33)) -> 335000
A34: 46127 | B34: =IF(A34="","",TEXT(A34,"dddd")) -> Wednesday | C34: Weekly allowance | D34: Money | E34: 700000 | G34: =IF(A34="","",$E$3+SUM($E$9:E34)-SUM($F$9:F34)) -> 1035000
A35: 46127 | B35: =IF(A35="","",TEXT(A35,"dddd")) -> Wednesday | C35: Meals | F35: 50000 | G35: =IF(A35="","",$E$3+SUM($E$9:E35)-SUM($F$9:F35)) -> 985000
A36: 46127 | B36: =IF(A36="","",TEXT(A36,"dddd")) -> Wednesday | C36: Meals | F36: 50000 | G36: =IF(A36="","",$E$3+SUM($E$9:E36)-SUM($F$9:F36)) -> 935000
A37: 46128 | B37: =IF(A37="","",TEXT(A37,"dddd")) -> Thursday | C37: Coffee | F37: 30000 | G37: =IF(A37="","",$E$3+SUM($E$9:E37)-SUM($F$9:F37)) -> 905000
A38: 46129 | B38: =IF(A38="","",TEXT(A38,"dddd")) -> Friday | C38: Meals | F38: 50000 | G38: =IF(A38="","",$E$3+SUM($E$9:E38)-SUM($F$9:F38)) -> 855000
A39: 46130 | B39: =IF(A39="","",TEXT(A39,"dddd")) -> Saturday | C39: Meals | F39: 50000 | G39: =IF(A39="","",$E$3+SUM($E$9:E39)-SUM($F$9:F39)) -> 805000
A40: 46133 | B40: =IF(A40="","",TEXT(A40,"dddd")) -> Tuesday | C40: BBQ | F40: 150000 | G40: =IF(A40="","",$E$3+SUM($E$9:E40)-SUM($F$9:F40)) -> 655000
A41: 46134 | B41: =IF(A41="","",TEXT(A41,"dddd")) -> Wednesday | C41: Weekly allowance | D41: Money | E41: 700000 | G41: =IF(A41="","",$E$3+SUM($E$9:E41)-SUM($F$9:F41)) -> 1355000
A42: 46134 | B42: =IF(A42="","",TEXT(A42,"dddd")) -> Wednesday | C42: Meals | F42: 70000 | G42: =IF(A42="","",$E$3+SUM($E$9:E42)-SUM($F$9:F42)) -> 1285000
A43: 46134 | B43: =IF(A43="","",TEXT(A43,"dddd")) -> Wednesday | C43: Coffee | F43: 30000 | G43: =IF(A43="","",$E$3+SUM($E$9:E43)-SUM($F$9:F43)) -> 1255000
A44: 46134 | B44: =IF(A44="","",TEXT(A44,"dddd")) -> Wednesday | C44: Document Copy | F44: 22000 | G44: =IF(A44="","",$E$3+SUM($E$9:E44)-SUM($F$9:F44)) -> 1233000
A45: 46135 | B45: =IF(A45="","",TEXT(A45,"dddd")) -> Thursday | C45: Meals | F45: 50000 | G45: =IF(A45="","",$E$3+SUM($E$9:E45)-SUM($F$9:F45)) -> 1183000
A46: 46136 | B46: =IF(A46="","",TEXT(A46,"dddd")) -> Friday | C46: Meals | F46: 50000 | G46: =IF(A46="","",$E$3+SUM($E$9:E46)-SUM($F$9:F46)) -> 1133000
A47: 46137 | B47: =IF(A47="","",TEXT(A47,"dddd")) -> Saturday | C47: Meals | F47: 50000 | G47: =IF(A47="","",$E$3+SUM($E$9:E47)-SUM($F$9:F47)) -> 1083000
A48: 46138 | B48: =IF(A48="","",TEXT(A48,"dddd")) -> Sunday | C48: Meals | F48: 50000 | G48: =IF(A48="","",$E$3+SUM($E$9:E48)-SUM($F$9:F48)) -> 1033000
A49: 46139 | B49: =IF(A49="","",TEXT(A49,"dddd")) -> Monday | C49: Meals | F49: 70000 | G49: =IF(A49="","",$E$3+SUM($E$9:E49)-SUM($F$9:F49)) -> 963000
A50: 46139 | B50: =IF(A50="","",TEXT(A50,"dddd")) -> Monday | C50: Party | F50: 200000 | G50: =IF(A50="","",$E$3+SUM($E$9:E50)-SUM($F$9:F50)) -> 763000
A51: 46141 | B51: =IF(A51="","",TEXT(A51,"dddd")) -> Wednesday | C51: Weekly allowance | D51: Money | E51: 700000 | G51: =IF(A51="","",$E$3+SUM($E$9:E51)-SUM($F$9:F51)) -> 1463000
A52: 46141 | B52: =IF(A52="","",TEXT(A52,"dddd")) -> Wednesday | C52: Meals | F52: 50000 | G52: =IF(A52="","",$E$3+SUM($E$9:E52)-SUM($F$9:F52)) -> 1413000
A53: 46141 | B53: =IF(A53="","",TEXT(A53,"dddd")) -> Wednesday | C53: Coffee | F53: 30000 | G53: =IF(A53="","",$E$3+SUM($E$9:E53)-SUM($F$9:F53)) -> 1383000
A54: 46141 | B54: =IF(A54="","",TEXT(A54,"dddd")) -> Wednesday | C54: Snack | F54: 15000 | G54: =IF(A54="","",$E$3+SUM($E$9:E54)-SUM($F$9:F54)) -> 1368000
A55: 46142 | B55: =IF(A55="","",TEXT(A55,"dddd")) -> Thursday | C55: Meals | F55: 50000 | G55: =IF(A55="","",$E$3+SUM($E$9:E55)-SUM($F$9:F55)) -> 1318000
A56: 46143 | B56: =IF(A56="","",TEXT(A56,"dddd")) -> Friday | C56: Meals | F56: 50000 | G56: =IF(A56="","",$E$3+SUM($E$9:E56)-SUM($F$9:F56)) -> 1268000
A57: 46144 | B57: =IF(A57="","",TEXT(A57,"dddd")) -> Saturday | C57: Meals | F57: 50000 | G57: =IF(A57="","",$E$3+SUM($E$9:E57)-SUM($F$9:F57)) -> 1218000
A58: 46145 | B58: =IF(A58="","",TEXT(A58,"dddd")) -> Sunday | C58: Coffee | F58: 50000 | G58: =IF(A58="","",$E$3+SUM($E$9:E58)-SUM($F$9:F58)) -> 1168000
A59: 46146 | B59: =IF(A59="","",TEXT(A59,"dddd")) -> Monday | C59: Meals | F59: 50000 | G59: =IF(A59="","",$E$3+SUM($E$9:E59)-SUM($F$9:F59)) -> 1118000
A60: 46146 | B60: =IF(A60="","",TEXT(A60,"dddd")) -> Monday | C60: Snack | F60: 30000 | G60: =IF(A60="","",$E$3+SUM($E$9:E60)-SUM($F$9:F60)) -> 1088000
A61: 46146 | B61: =IF(A61="","",TEXT(A61,"dddd")) -> Monday | C61: Meals | F61: 50000 | G61: =IF(A61="","",$E$3+SUM($E$9:E61)-SUM($F$9:F61)) -> 1038000
A62: 46147 | B62: =IF(A62="","",TEXT(A62,"dddd")) -> Tuesday | C62: Meals | F62: 50000 | G62: =IF(A62="","",$E$3+SUM($E$9:E62)-SUM($F$9:F62)) -> 988000
A63: 46147 | B63: =IF(A63="","",TEXT(A63,"dddd")) -> Tuesday | C63: Document Copy | F63: 60000 | G63: =IF(A63="","",$E$3+SUM($E$9:E63)-SUM($F$9:F63)) -> 928000
... A65: 46148 | B65: =IF(A65="","",TEXT(A65,"dddd")) -> Wednesday | C65: Movie ticket | F65: 70000 | G65: =IF(A65="","",$E$3+SUM($E$9:E65)-SUM($F$9:F65)) -> 808000
A66: 46148 | B66: =IF(A66="","",TEXT(A66,"dddd")) -> Wednesday | C66: Weekly allowance | D66: Money | E66: 700000 | G66: =IF(A66="","",$E$3+SUM($E$9:E66)-SUM($F$9:F66)) -> 1508000
A67: 46149 | B67: =IF(A67="","",TEXT(A67,"dddd")) -> Thursday | C67: Meals | F67: 50000 | G67: =IF(A67="","",$E$3+SUM($E$9:E67)-SUM($F$9:F67)) -> 1458000
A68: 46150 | B68: =IF(A68="","",TEXT(A68,"dddd")) -> Friday | C68: Meals | F68: 70000 | G68: =IF(A68="","",$E$3+SUM($E$9:E68)-SUM($F$9:F68)) -> 1388000
A69: 46150 | B69: =IF(A69="","",TEXT(A69,"dddd")) -> Friday | C69: Snack | F69: 40000 | G69: =IF(A69="","",$E$3+SUM($E$9:E69)-SUM($F$9:F69)) -> 1348000
A70: 46151 | B70: =IF(A70="","",TEXT(A70,"dddd")) -> Saturday | C70: Meals | F70: 70000 | G70: =IF(A70="","",$E$3+SUM($E$9:E70)-SUM($F$9:F70)) -> 1278000
A71: 46152 | B71: =IF(A71="","",TEXT(A71,"dddd")) -> Sunday | C71: Meals | F71: 120000 | G71: =IF(A71="","",$E$3+SUM($E$9:E71)-SUM($F$9:F71)) -> 1158000
A72: 46153 | B72: =IF(A72="","",TEXT(A72,"dddd")) -> Monday | C72: Coffee | F72: 50000 | G72: =IF(A72="","",$E$3+SUM($E$9:E72)-SUM($F$9:F72)) -> 1108000
A73: 46153 | B73: =IF(A73="","",TEXT(A73,"dddd")) -> Monday | C73: Meals | F73: 50000 | G73: =IF(A73="","",$E$3+SUM($E$9:E73)-SUM($F$9:F73)) -> 1058000
A74: 46153 | B74: =IF(A74="","",TEXT(A74,"dddd")) -> Monday | C74: Meals | F74: 50000 | G74: =IF(A74="","",$E$3+SUM($E$9:E74)-SUM($F$9:F74)) -> 1008000
A75: 46154 | B75: =IF(A75="","",TEXT(A75,"dddd")) -> Tuesday | C75: Movie ticket | F75: 70000 | G75: =IF(A75="","",$E$3+SUM($E$9:E75)-SUM($F$9:F75)) -> 938000
A76: 46154 | B76: =IF(A76="","",TEXT(A76,"dddd")) -> Tuesday | C76: Meals | F76: 55000 | G76: =IF(A76="","",$E$3+SUM($E$9:E76)-SUM($F$9:F76)) -> 883000
A77: 46155 | B77: =IF(A77="","",TEXT(A77,"dddd")) -> Wednesday | C77: Weekly allowance | D77: Money | E77: 700000 | G77: =IF(A77="","",$E$3+SUM($E$9:E77)-SUM($F$9:F77)) -> 1583000
A78: 46155 | B78: =IF(A78="","",TEXT(A78,"dddd")) -> Wednesday | C78: Meals | F78: 70000 | G78: =IF(A78="","",$E$3+SUM($E$9:E78)-SUM($F$9:F78)) -> 1513000
A79: 46155 | B79: =IF(A79="","",TEXT(A79,"dddd")) -> Wednesday | C79: Coffee | F79: 50000 | G79: =IF(A79="","",$E$3+SUM($E$9:E79)-SUM($F$9:F79)) -> 1463000
A80: 46156 | B80: =IF(A80="","",TEXT(A80,"dddd")) -> Thursday | C80: Meals | F80: 50000 | G80: =IF(A80="","",$E$3+SUM($E$9:E80)-SUM($F$9:F80)) -> 1413000
A81: 46156 | B81: =IF(A81="","",TEXT(A81,"dddd")) -> Thursday | C81: Snack | F81: 50000 | G81: =IF(A81="","",$E$3+SUM($E$9:E81)-SUM($F$9:F81)) -> 1363000
A82: 46157 | B82: =IF(A82="","",TEXT(A82,"dddd")) -> Friday | C82: Meals | F82: 60000 | G82: =IF(A82="","",$E$3+SUM($E$9:E82)-SUM($F$9:F82)) -> 1303000
A83: 46157 | B83: =IF(A83="","",TEXT(A83,"dddd")) -> Friday | C83: Party | F83: 200000 | G83: =IF(A83="","",$E$3+SUM($E$9:E83)-SUM($F$9:F83)) -> 1103000
A84: 46158 | B84: =IF(A84="","",TEXT(A84,"dddd")) -> Saturday | C84: Meals | F84: 60000 | G84: =IF(A84="","",$E$3+SUM($E$9:E84)-SUM($F$9:F84)) -> 1043000
A85: 46159 | B85: =IF(A85="","",TEXT(A85,"dddd")) -> Sunday | C85: Meals | F85: 60000 | G85: =IF(A85="","",$E$3+SUM($E$9:E85)-SUM($F$9:F85)) -> 983000
A86: 46160 | B86: =IF(A86="","",TEXT(A86,"dddd")) -> Monday | C86: Coffee | F86: 40000 | G86: =IF(A86="","",$E$3+SUM($E$9:E86)-SUM($F$9:F86)) -> 943000
A87: 46160 | B87: =IF(A87="","",TEXT(A87,"dddd")) -> Monday | C87: Meals | F87: 50000 | G87: =IF(A87="","",$E$3+SUM($E$9:E87)-SUM($F$9:F87)) -> 893000
A88: 46161 | B88: =IF(A88="","",TEXT(A88,"dddd")) -> Tuesday | C88: Meals | F88: 50000 | G88: =IF(A88="","",$E$3+SUM($E$9:E88)-SUM($F$9:F88)) -> 843000
A89: 46162 | B89: =IF(A89="","",TEXT(A89,"dddd")) -> Wednesday | C89: Weekly allowance | D89: Money | E89: 700000 | G89: =IF(A89="","",$E$3+SUM($E$9:E89)-SUM($F$9:F89)) -> 1543000
A90: 46162 | B90: =IF(A90="","",TEXT(A90,"dddd")) -> Wednesday | C90: Meals | F90: 50000 | G90: =IF(A90="","",$E$3+SUM($E$9:E90)-SUM($F$9:F90)) -> 1493000
A91: 46162 | B91: =IF(A91="","",TEXT(A91,"dddd")) -> Wednesday | C91: Coffee | F91: 40000 | G91: =IF(A91="","",$E$3+SUM($E$9:E91)-SUM($F$9:F91)) -> 1453000
A92: 46163 | B92: =IF(A92="","",TEXT(A92,"dddd")) -> Thursday | C92: Meals | F92: 50000 | G92: =IF(A92="","",$E$3+SUM($E$9:E92)-SUM($F$9:F92)) -> 1403000
A93: 46165 | B93: =IF(A93="","",TEXT(A93,"dddd")) -> Saturday | C93: Meals | F93: 50000 | G93: =IF(A93="","",$E$3+SUM($E$9:E93)-SUM($F$9:F93)) -> 1353000
A94: 46165 | B94: =IF(A94="","",TEXT(A94,"dddd")) -> Saturday | C94: Snack | F94: 50000 | G94: =IF(A94="","",$E$3+SUM($E$9:E94)-SUM($F$9:F94)) -> 1303000
A95: 46166 | B95: =IF(A95="","",TEXT(A95,"dddd")) -> Sunday | C95: Movie ticket | F95: 70000 | G95: =IF(A95="","",$E$3+SUM($E$9:E95)-SUM($F$9:F95)) -> 1233000
A96: 46167 | B96: =IF(A96="","",TEXT(A96,"dddd")) -> Monday | C96: Coffee | F96: 45000 | G96: =IF(A96="","",$E$3+SUM($E$9:E96)-SUM($F$9:F96)) -> 1188000
A97: 46167 | B97: =IF(A97="","",TEXT(A97,"dddd")) -> Monday | C97: Meals | F97: 50000 | G97: =IF(A97="","",$E$3+SUM($E$9:E97)-SUM($F$9:F97)) -> 1138000
A98: 46168 | B98: =IF(A98="","",TEXT(A98,"dddd")) -> Tuesday | C98: Meals | F98: 50000 | G98: =IF(A98="","",$E$3+SUM($E$9:E98)-SUM($F$9:F98)) -> 1088000
A99: 46168 | B99: =IF(A99="","",TEXT(A99,"dddd")) -> Tuesday | C99: Snack | F99: 20000 | G99: =IF(A99="","",$E$3+SUM($E$9:E99)-SUM($F$9:F99)) -> 1068000
A100: 46169 | B100: =IF(A100="","",TEXT(A100,"dddd")) -> Wednesday | C100: Weekly allowance | D100: Money | E100: 700000 | G100: =IF(A100="","",$E$3+SUM($E$9:E100)-SUM($F$9:F100)) -> 1768000
A101: 46169 | B101: =IF(A101="","",TEXT(A101,"dddd")) -> Wednesday | C101: Meals | F101: 100000 | G101: =IF(A101="","",$E$3+SUM($E$9:E101)-SUM($F$9:F101)) -> 1668000
A102: 46169 | B102: =IF(A102="","",TEXT(A102,"dddd")) -> Wednesday | C102: Youtube premium | F102: 55000 | G102: =IF(A102="","",$E$3+SUM($E$9:E102)-SUM($F$9:F102)) -> 1613000
A103: 46169 | B103: =IF(A103="","",TEXT(A103,"dddd")) -> Wednesday | C103: Netflix | F103: 220000 | G103: =IF(A103="","",$E$3+SUM($E$9:E103)-SUM($F$9:F103)) -> 1393000
A104: 46169 | B104: =IF(A104="","",TEXT(A104,"dddd")) -> Wednesday | C104: New shirt | F104: 150000 | G104: =IF(A104="","",$E$3+SUM($E$9:E104)-SUM($F$9:F104)) -> 1243000
...

Sheet Monthly
A3: ປີ (ຄ.ສ.) | B3: 2026 | D3: ເລືອກວັນທີ່ | E3: 46113
A4: ເດືອນ (1-12) | B4: 4 | D4: ລາຍຮັບມື້ນັ້ນ | E4: =SUMIFS(Clashbook!$E$9:$E$508,Clashbook!$A$9:$A$508,E3) -> 700000
A5: ມື້ແລກຂອງເດືອນ | B5: =DATE(B3,B4,1) -> 46113 | D5: ລາຍຈ່າຍມື້ນັ້ນ | E5: =SUMIFS(Clashbook!$F$9:$F$508,Clashbook!$A$9:$A$508,E3) -> 130000
A6: ມື້ສຸດທ້າຍຂອງເດືອນ | B6: =EOMONTH(B5,0) -> 46142 | D6: ຈຳນວນລາຍການມື້ນັ້ນ | E6: =COUNTIFS(Clashbook!$A$9:$A$508,E3) -> 4
A7: ຈຳນວນມື້ | B7: =DAY(B6) -> 30 | D7: ຈ່າຍສະສົມຕົ້ນເດືອນຮອດມື້ນັ້ນ | E7: =SUMIFS(Clashbook!$F$9:$F$508,Clashbook!$A$9:$A$508,">="&B5,Clashbook!$A$9:$A$508,"<="&E3) -> 130000
A9: ວັນທີ່ | B9: ລາຍຮັບ | C9: ລາຍຈ່າຍ | D9: ສຸດທິ | E9: ຈຳນວນລາຍການ
A10: =B5 -> 46113 | B10: =IF(A10="","",SUMIFS(Clashbook!$E$9:$E$508,Clashbook!$A$9:$A$508,A10)) -> 700000 | C10: =IF(A10="","",SUMIFS(Clashbook!$F$9:$F$508,Clashbook!$A$9:$A$508,A10)) -> 130000 | D10: =IF(A10="","",B10-C10) -> 570000 | E10: =IF(A10="","",COUNTIFS(Clashbook!$A$9:$A$508,A10)) -> 4
A11: =IF(A10="","",IF(A10+1>$B$6,"",A10+1)) -> 46114 | B11: =IF(A11="","",SUMIFS(Clashbook!$E$9:$E$508,Clashbook!$A$9:$A$508,A11)) -> 0 | C11: =IF(A11="","",SUMIFS(Clashbook!$F$9:$F$508,Clashbook!$A$9:$A$508,A11)) -> 135000 | D11: =IF(A11="","",B11-C11) -> -135000 | E11: =IF(A11="","",COUNTIFS(Clashbook!$A$9:$A$508,A11)) -> 4
A12: =IF(A11="","",IF(A11+1>$B$6,"",A11+1)) -> 46115 | B12: =IF(A12="","",SUMIFS(Clashbook!$E$9:$E$508,Clashbook!$A$9:$A$508,A12)) -> 0 | C12: =IF(A12="","",SUMIFS(Clashbook!$F$9:$F$508,Clashbook!$A$9:$A$508,A12)) -> 90000 | D12: =IF(A12="","",B12-C12) -> -90000 | E12: =IF(A12="","",COUNTIFS(Clashbook!$A$9:$A$508,A12)) -> 3
A13: =IF(A12="","",IF(A12+1>$B$6,"",A12+1)) -> 46116 | B13: =IF(A13="","",SUMIFS(Clashbook!$E$9:$E$508,Clashbook!$A$9:$A$508,A13)) -> 0 | C13: =IF(A13="","",SUMIFS(Clashbook!$F$9:$F$508,Clashbook!$A$9:$A$508,A13)) -> 100000 | D13: =IF(A13="","",B13-C13) -> -100000 | E13: =IF(A13="","",COUNTIFS(Clashbook!$A$9:$A$508,A13)) -> 2
A14: =IF(A13="","",IF(A13+1>$B$6,"",A13+1)) -> 46117 | B14: =IF(A14="","",SUMIFS(Clashbook!$E$9:$E$508,Clashbook!$A$9:$A$508,A14)) -> 0 | C14: =IF(A14="","",SUMIFS(Clashbook!$F$9:$F$508,Clashbook!$A$9:$A$508,A14)) -> 80000 | D14: =IF(A14="","",B14-C14) -> -80000 | E14: =IF(A14="","",COUNTIFS(Clashbook!$A$9:$A$508,A14)) -> 2
A15: =IF(A14="","",IF(A14+1>$B$6,"",A14+1)) -> 46118 | B15: =IF(A15="","",SUMIFS(Clashbook!$E$9:$E$508,Clashbook!$A$9:$A$508,A15)) -> 0 | C15: =IF(A15="","",SUMIFS(Clashbook!$F$9:$F$508,Clashbook!$A$9:$A$508,A15)) -> 50000 | D15: =IF(A15="","",B15-C15) -> -50000 | E15: =IF(A15="","",COUNTIFS(Clashbook!$A$9:$A$508,A15)) -> 1
A16: =IF(A15="","",IF(A15+1>$B$6,"",A15+1)) -> 46119 | B16: =IF(A16="","",SUMIFS(Clashbook!$E$9:$E$508,Clashbook!$A$9:$A$508,A16)) -> 0 | C16: =IF(A16="","",SUMIFS(Clashbook!$F$9:$F$508,Clashbook!$A$9:$A$508,A16)) -> 0 | D16: =IF(A16="","",B16-C16) -> 0 | E16: =IF(A16="","",COUNTIFS(Clashbook!$A$9:$A$508,A16)) -> 0
A17: =IF(A16="","",IF(A16+1>$B$6,"",A16+1)) -> 46120 | B17: =IF(A17="","",SUMIFS(Clashbook!$E$9:$E$508,Clashbook!$A$9:$A$508,A17)) -> 700000 | C17: =IF(A17="","",SUMIFS(Clashbook!$F$9:$F$508,Clashbook!$A$9:$A$508,A17)) -> 50000 | D17: =IF(A17="","",B17-C17) -> 650000 | E17: =IF(A17="","",COUNTIFS(Clashbook!$A$9:$A$508,A17)) -> 2
A18: =IF(A17="","",IF(A17+1>$B$6,"",A17+1)) -> 46121 | B18: =IF(A18="","",SUMIFS(Clashbook!$E$9:$E$508,Clashbook!$A$9:$A$508,A18)) -> 0 | C18: =IF(A18="","",SUMIFS(Clashbook!$F$9:$F$508,Clashbook!$A$9:$A$508,A18)) -> 80000 | D18: =IF(A18="","",B18-C18) -> -80000 | E18: =IF(A18="","",COUNTIFS(Clashbook!$A$9:$A$508,A18)) -> 2
A19: =IF(A18="","",IF(A18+1>$B$6,"",A18+1)) -> 46122 | B19: =IF(A19="","",SUMIFS(Clashbook!$E$9:$E$508,Clashbook!$A$9:$A$508,A19)) -> 0 | C19: =IF(A19="","",SUMIFS(Clashbook!$F$9:$F$508,Clashbook!$A$9:$A$508,A19)) -> 50000 | D19: =IF(A19="","",B19-C19) -> -50000 | E19: =IF(A19="","",COUNTIFS(Clashbook!$A$9:$A$508,A19)) -> 1
A20: =IF(A19="","",IF(A19+1>$B$6,"",A19+1)) -> 46123 | B20: =IF(A20="","",SUMIFS(Clashbook!$E$9:$E$508,Clashbook!$A$9:$A$508,A20)) -> 0 | C20: =IF(A20="","",SUMIFS(Clashbook!$F$9:$F$508,Clashbook!$A$9:$A$508,A20)) -> 50000 | D20: =IF(A20="","",B20-C20) -> -50000 | E20: =IF(A20="","",COUNTIFS(Clashbook!$A$9:$A$508,A20)) -> 1
A21: =IF(A20="","",IF(A20+1>$B$6,"",A20+1)) -> 46124 | B21: =IF(A21="","",SUMIFS(Clashbook!$E$9:$E$508,Clashbook!$A$9:$A$508,A21)) -> 0 | C21: =IF(A21="","",SUMIFS(Clashbook!$F$9:$F$508,Clashbook!$A$9:$A$508,A21)) -> 50000 | D21: =IF(A21="","",B21-C21) -> -50000 | E21: =IF(A21="","",COUNTIFS(Clashbook!$A$9:$A$508,A21)) -> 1
A22: =IF(A21="","",IF(A21+1>$B$6,"",A21+1)) -> 46125 | B22: =IF(A22="","",SUMIFS(Clashbook!$E$9:$E$508,Clashbook!$A$9:$A$508,A22)) -> 0 | C22: =IF(A22="","",SUMIFS(Clashbook!$F$9:$F$508,Clashbook!$A$9:$A$508,A22)) -> 150000 | D22: =IF(A22="","",B22-C22) -> -150000 | E22: =IF(A22="","",COUNTIFS(Clashbook!$A$9:$A$508,A22)) -> 1
... A40: =IF(A39="","",IF(A39+1>$B$6,"",A39+1)) | B40: =IF(A40="","",SUMIFS(Clashbook!$E$9:$E$508,Clashbook!$A$9:$A$508,A40)) | C40: =IF(A40="","",SUMIFS(Clashbook!$F$9:$F$508,Clashbook!$A$9:$A$508,A40)) | D40: =IF(A40="","",B40-C40) | E40: =IF(A40="","",COUNTIFS(Clashbook!$A$9:$A$508,A40))
A41: ລວມທັງເດືອນ | B41: =SUM(B10:B40) -> 3500000 | C41: =SUM(C10:C40) -> 2182000 | D41: =SUM(D10:D40) -> 1318000 | E41: =SUM(E10:E40) -> 47
A43: ວັນທີ່ມີລາຍການ | B43: =COUNTIF(E10:E40,">0") -> 26
A44: ລາຍຈ່າຍສະເລ່ຍຕໍ່ມື້ | B44: =IFERROR(C41/B7,0) -> 72733.333
A45: Check (ຕ້ອງ = 0) | B45: =ROUND(C41-SUMIFS(Clashbook!$F$9:$F$508,Clashbook!$A$9:$A$508,">="&B5,Clashbook!$A$9:$A$508,"<="&B6),2) -> 0

Sheet Tax
A5: ອັດຕາ Vat | B5: 0.07
A6: ອັດຕາຫັກຂະນະທີ່ຈ່າຍ | B6: 0.03
A9: ລາຄາສິນຄ້າ (ກ່ອນ Vat) | B9: 100000
A10: Vat | B10: =ROUND(B9*$B$5,2) -> 7000
A11: ຍອດລວມທີ່ລູກຄ້າຈ່າຍ | B11: =B9+B10 -> 107000
A14: ລາຄາປ້າຍ (ລວມ Vat ແລ້ວ) | B14: 100000
A15: ລາຄາກ່ອນ Vat | B15: =ROUND(B14/(1+$B$5),2) -> 93457.94
A16: VAT | B16: =B14-B15 -> 6542.06
A20: ຄ່າບໍລິການ (ກ່ອນ Vat) | B20: 100000
A21: ບວກ Vat | B21: =ROUND(B20*$B$5,2) -> 7000
A22: ຍອດຕາມໃບກຳກັບພາສີ | B22: =B20+B21 -> 107000
A23: ຫັກຂະນະທີ່ຈ່າຍ | B23: =ROUND(B20*$B$6,2) -> 3000
A24: ຍອດໂອນຈ່າຍຈິງ | B24: =B22-B23 -> 104000

Sheet VAT Report
A4: Date | B4: Doc No. | C4: List | D4: Type | E4: Amount (ກ່ອນ VAT) | F4: VAT | G4: Total
A5: 46113 | B5: INV-001 | C5: ຂາຍສິນຄ້າໃຫ້ຮ້ານ A | D5: Sales | E5: 5000000 | F5: =IF(E5="","",ROUND(E5*Tax!$B$5,2)) -> 350000 | G5: =IF(E5="","",E5+F5) -> 5350000 | I5: ຍອດຂາຍ | J5: =SUMIFS($E$5:$E$104,$D$5:$D$104,"Sales") -> 20000000
A6: 46115 | B6: PO-001 | C6: ຊື້ວັດຖຸດິບ | D6: Purchase | E6: 2000000 | F6: =IF(E6="","",ROUND(E6*Tax!$B$5,2)) -> 140000 | G6: =IF(E6="","",E6+F6) -> 2140000 | I6: ພາສີຂາຍ | J6: =SUMIFS($F$5:$F$104,$D$5:$D$104,"Sales") -> 1400000
A7: 46120 | B7: INV-002 | C7: ຂາຍສິນຄ້າໃຫ້ຮ້ານ B | D7: Sales | E7: 3000000 | F7: =IF(E7="","",ROUND(E7*Tax!$B$5,2)) -> 210000 | G7: =IF(E7="","",E7+F7) -> 3210000 | I7: ຍອດຊື້ | J7: =SUMIFS($E$5:$E$104,$D$5:$D$104,"Purchase") -> 10000000
A8: 46124 | B8: PO-002 | C8: ຊື້ສິນຄ້າເຂົ້າຮ້ານ | D8: Purchase | E8: 15000000 | F8: =IF(E8="","",ROUND(E8*Tax!$B$5,2)) -> 1050000 | G8: =IF(E8="","",E8+F8) -> 16050000 | I8: ພາສີຊື້ | J8: =SUMIFS($F$5:$F$104,$D$5:$D$104,"Purchase") -> 700000
A9: 46132 | B9: INV-003 | C9: ຂາຍສິນຄ້າໃຫ້ຮ້ານ B | D9: Sales | E9: 12000000 | F9: =IF(E9="","",ROUND(E9*Tax!$B$5,2)) -> 840000 | G9: =IF(E9="","",E9+F9) -> 12840000 | I9: ພາສີທີ່ຕ້ອງຊຳລະ | J9: =J6-J8 -> 700000
A10: 46137 | B10: PO-003 | C10: ຄ່າແປງອຸປະກອນ | D10: Purchase | E10: 8000000 | F10: =IF(E10="","",ROUND(E10*Tax!$B$5,2)) -> 560000 | G10: =IF(E10="","",E10+F10) -> 8560000 | I10: ສະຖານະ | J10: =IF(J9>0,"ຕ້ອງຊຳລະພາສີ",IF(J9<0,"ມີເຄດິດພາສີຍົກໄປເດືອນຫນ້າ","ບໍ່ມີຍອດ")) -> ຕ້ອງຊຳລະພາສີ
F11: =IF(E11="","",ROUND(E11*Tax!$B$5,2)) | G11: =IF(E11="","",E11+F11)
F12: =IF(E12="","",ROUND(E12*Tax!$B$5,2)) | G12: =IF(E12="","",E12+F12)
F13: =IF(E13="","",ROUND(E13*Tax!$B$5,2)) | G13: =IF(E13="","",E13+F13)
F14: =IF(E14="","",ROUND(E14*Tax!$B$5,2)) | G14: =IF(E14="","",E14+F14)
F15: =IF(E15="","",ROUND(E15*Tax!$B$5,2)) | G15: =IF(E15="","",E15+F15)
F16: =IF(E16="","",ROUND(E16*Tax!$B$5,2)) | G16: =IF(E16="","",E16+F16)
F17: =IF(E17="","",ROUND(E17*Tax!$B$5,2)) | G17: =IF(E17="","",E17+F17)
F18: =IF(E18="","",ROUND(E18*Tax!$B$5,2)) | G18: =IF(E18="","",E18+F18)
F19: =IF(E19="","",ROUND(E19*Tax!$B$5,2)) | G19: =IF(E19="","",E19+F19)
F20: =IF(E20="","",ROUND(E20*Tax!$B$5,2)) | G20: =IF(E20="","",E20+F20)
F21: =IF(E21="","",ROUND(E21*Tax!$B$5,2)) | G21: =IF(E21="","",E21+F21)
F22: =IF(E22="","",ROUND(E22*Tax!$B$5,2)) | G22: =IF(E22="","",E22+F22)
... F104: =IF(E104="","",ROUND(E104*Tax!$B$5,2)) | G104: =IF(E104="","",E104+F104)

Sheet Category
A1: Category
A2: Sales
A3: Other Income
A4: Raw Material
A5: Wages
A6: Supplies
A7: Utilities
A8: Rent
A9: Weekly allowance
A10: Money
